kublah/main.py
kublah-0.1.0.dist-info/METADATA
kublah-0.1.0.dist-info/WHEEL
kublah-0.1.0.dist-info/entry_points.txt
kublah-0.1.0.dist-info/RECORD
