Metadata-Version: 2.1
Name: kublah
Version: 0.1.0
Summary: kublah is a command line tool kit that generates kubernetes commands based on your nature language request.
Author: Jingkai
Author-email: jingkai@hey.com
Requires-Python: >=3.12,<4.0
Classifier: Programming Language :: Python :: 3
Classifier: Programming Language :: Python :: 3.12
Requires-Dist: instructor (>=1.3.4,<2.0.0)
Requires-Dist: jinja2 (>=3.1.3,<4.0.0)
Requires-Dist: openai (>=1.23.2,<2.0.0)
Requires-Dist: pyyaml (>=6.0.1,<7.0.0)
